otto/__init__.py
otto/__main__.py
otto/adhd_support.py
otto/agent_coordinator.py
otto/bulkhead.py
otto/checkpoint.py
otto/claude_code_hook.py
otto/cognitive_orchestrator.py
otto/cognitive_stage.py
otto/cognitive_state.py
otto/cognitive_support.py
otto/cogroute_bench.py
otto/config.py
otto/convergence_tracker.py
otto/dashboard.py
otto/dashboard_bridge.py
otto/decision_engine.py
otto/expert_router.py
otto/fallback.py
otto/file_ops.py
otto/framework_orchestrator.py
otto/health.py
otto/http_server.py
otto/idempotency.py
otto/lifecycle.py
otto/logging_setup.py
otto/metrics.py
otto/otel_adapter.py
otto/parameter_locker.py
otto/prism_detector.py
otto/profile_loader.py
otto/py.typed
otto/rate_limit.py
otto/research_agent.py
otto/resilience.py
otto/schemas.py
otto/synthesis_agent.py
otto/tension_surfacer.py
otto/tracing.py
otto/validation.py
otto/websocket_server.py
otto/agents/__init__.py
otto/agents/base.py
otto/agents/context_aware_coordinator.py
otto/agents/memory.py
otto/agents/planner.py
otto/agents/progress.py
otto/agents/reflection.py
otto/agents/researcher.py
otto/api/__init__.py
otto/api/api_keys.py
otto/api/audit.py
otto/api/errors.py
otto/api/frontier_crypto.py
otto/api/merkle_audit.py
otto/api/middleware.py
otto/api/mobile.py
otto/api/openapi.py
otto/api/push.py
otto/api/rate_limit_backend.py
otto/api/response.py
otto/api/rest_router.py
otto/api/schemas.py
otto/api/scopes.py
otto/api/security.py
otto/api/security_posture.py
otto/api/self_healing.py
otto/api/threshold_signatures.py
otto/api/tls.py
otto/api/webauthn.py
otto/api/websocket.py
otto/calibration/__init__.py
otto/calibration/calibration_learner.py
otto/calibration/calibration_manager.py
otto/calibration/calibration_store.py
otto/calibration/outcome_tracker.py
otto/cli/__init__.py
otto/cli/interactive.py
otto/cli/main.py
otto/cli/status.py
otto/cli/tui.py
otto/cli/tui_bridge.py
otto/cli/tui_enhanced.py
otto/crypto/__init__.py
otto/crypto/encryption.py
otto/crypto/key_derivation.py
otto_os-0.6.0.dist-info/licenses/LICENSE
otto_os-0.6.0.dist-info/METADATA
otto_os-0.6.0.dist-info/WHEEL
otto_os-0.6.0.dist-info/entry_points.txt
otto_os-0.6.0.dist-info/top_level.txt
otto_os-0.6.0.dist-info/RECORD
