Metadata-Version: 2.4
Name: otto-os
Version: 0.6.0
Summary: Personal OS with cognitive protection - Built on Orchestra foundations
Author: OTTO OS Contributors
License: MIT
Project-URL: Homepage, https://github.com/JosephOIbrahim/otto-os
Project-URL: Bug Tracker, https://github.com/JosephOIbrahim/otto-os/issues
Keywords: personal-os,cognitive-safety,agents,adhd,burnout-protection,usd
Classifier: Development Status :: 3 - Alpha
Classifier: Intended Audience :: End Users/Desktop
Classifier: License :: OSI Approved :: MIT License
Classifier: Operating System :: OS Independent
Classifier: Programming Language :: Python :: 3
Classifier: Programming Language :: Python :: 3.10
Classifier: Programming Language :: Python :: 3.11
Classifier: Programming Language :: Python :: 3.12
Classifier: Topic :: Scientific/Engineering :: Artificial Intelligence
Classifier: Topic :: Utilities
Requires-Python: >=3.10
License-File: LICENSE
Requires-Dist: aiohttp>=3.8.0
Requires-Dist: msgpack>=1.0.0
Requires-Dist: pydantic>=2.0.0
Requires-Dist: rich>=13.0.0
Requires-Dist: cryptography>=41.0.0
Requires-Dist: argon2-cffi>=23.0.0
Requires-Dist: keyring>=24.0.0
Provides-Extra: dev
Requires-Dist: pytest>=7.0.0; extra == "dev"
Requires-Dist: pytest-asyncio>=0.21.0; extra == "dev"
Requires-Dist: pytest-cov>=4.0.0; extra == "dev"
Requires-Dist: hypothesis>=6.100.0; extra == "dev"
Provides-Extra: tui
Requires-Dist: textual>=0.40.0; extra == "tui"
Provides-Extra: frontier
Provides-Extra: frontier-full
Requires-Dist: liboqs-python>=0.10.0; extra == "frontier-full"
Requires-Dist: python-pkcs11>=0.7.0; extra == "frontier-full"
Dynamic: license-file
